Buche_Silberstein_model_2020/__init__.py
Buche_Silberstein_model_2020/__main__.py
Buche_Silberstein_model_2020/constitutive_model.py
Buche_Silberstein_model_2020/miscellaneous.py
Buche_Silberstein_model_2020/single_chain.py
Buche_Silberstein_model_2020-1.0.1.dist-info/METADATA
Buche_Silberstein_model_2020-1.0.1.dist-info/WHEEL
Buche_Silberstein_model_2020-1.0.1.dist-info/top_level.txt
Buche_Silberstein_model_2020-1.0.1.dist-info/RECORD
