Metadata-Version: 2.1
Name: Buche-Silberstein-model-2020
Version: 1.0.1
Summary: This is the Python package corresponding to: Buche, Michael R., and Meredith N. Silberstein. Statistical mechanical constitutive theory of polymer networks: The inextricable links between distribution, behavior, and ensemble. Physical Review E, 102, 012501 (2020).
Home-page: https://github.com/mbuche/Buche_Silberstein_model_2020
Author: Michael R. Buche
Author-email: mrb289@cornell.edu
License: MIT
Platform: UNKNOWN
Classifier: License :: OSI Approved :: MIT License
Classifier: Programming Language :: Python :: 3
Classifier: Programming Language :: Python :: 3.7
Requires-Dist: numpy
Requires-Dist: scipy
